pyxin/__init__.py
pyxin/module.py
pyxin-0.0.1.dist-info/METADATA
pyxin-0.0.1.dist-info/RECORD
pyxin-0.0.1.dist-info/WHEEL
pyxin-0.0.1.dist-info/top_level.txt
