Metadata-Version: 2.1
Name: pyxin
Version: 0.0.1
Summary: a package of pyxin
Home-page: UNKNOWN
Author: UNKNOWN
Author-email: UNKNOWN
License: UNKNOWN
Platform: UNKNOWN
